PrinciplesOfComputerSystemDesignAnIntroductionPartIiMit6004/README.md
PrinciplesOfComputerSystemDesignAnIntroductionPartIiMit6004/__init__.py
PrinciplesOfComputerSystemDesignAnIntroductionPartIiMit6004/__main__.py
PrinciplesOfComputerSystemDesignAnIntroductionPartIiMit6004/file.pdf
PrinciplesOfComputerSystemDesignAnIntroductionPartIiMit6004/index.html
principles_of_computer_system_design_an_introduction_part_ii_mit_6_004-2024.3.2.0.dist-info/METADATA
principles_of_computer_system_design_an_introduction_part_ii_mit_6_004-2024.3.2.0.dist-info/WHEEL
principles_of_computer_system_design_an_introduction_part_ii_mit_6_004-2024.3.2.0.dist-info/entry_points.txt
principles_of_computer_system_design_an_introduction_part_ii_mit_6_004-2024.3.2.0.dist-info/top_level.txt
principles_of_computer_system_design_an_introduction_part_ii_mit_6_004-2024.3.2.0.dist-info/RECORD
